pvcastro_iberlef/__init__.py
pvcastro_iberlef/evaluate_ner.py
pvcastro_iberlef/iberlef_ner_input_reader.py
pvcastro_iberlef/predict_ner.py
pvcastro_iberlef/tagging_scheme.py
pvcastro_iberlef-0.4.1.dist-info/METADATA
pvcastro_iberlef-0.4.1.dist-info/WHEEL
pvcastro_iberlef-0.4.1.dist-info/top_level.txt
pvcastro_iberlef-0.4.1.dist-info/zip-safe
pvcastro_iberlef-0.4.1.dist-info/RECORD
