Metadata-Version: 2.1
Name: pvcastro-iberlef
Version: 0.4.1
Summary: System for the IberLEF 2019 NER Task
Home-page: http://www.inf.pucrs.br/linatural/wordpress/iberlef-2019/
Author: Pedro Vitor Quinta de Castro
Author-email: pvcastro@gmail.com
License: UNKNOWN
Platform: UNKNOWN
Requires-Dist: fire
